logzio/__init__.py
logzio/exceptions.py
logzio/flusher.py
logzio/handler.py
logzio/logger.py
logzio/sender.py
tests/__init__.py
tests/test_add_context.py
tests/test_extra_fields.py
tests/test_logzioHandler.py
tests/test_logzioSender.py
tests/mockLogzioListener/__init__.py
tests/mockLogzioListener/listener.py
tests/mockLogzioListener/logsList.py
tests/mockLogzioListener/persistentFlags.py
logzio_python_handler_akiva-4.1.2.dist-info/LICENSE
logzio_python_handler_akiva-4.1.2.dist-info/METADATA
logzio_python_handler_akiva-4.1.2.dist-info/WHEEL
logzio_python_handler_akiva-4.1.2.dist-info/top_level.txt
logzio_python_handler_akiva-4.1.2.dist-info/RECORD
